{
  "days": [
    {
      "day": 1,
      "times": [
        "7:00 AM",
        "11:00 AM",
        "3:00 PM",
        "7:00 PM"
      ],
      "id": "ddca"
    },
    {
      "day": 2,
      "times": [
        "8:00 AM",
        "12:00 PM",
        "4:00 PM",
        "8:00 PM"
      ],
      "id": "598b"
    },
    {
      "day": 3,
      "times": [
        "7:30 AM",
        "11:30 AM",
        "2:30 PM",
        "6:30 PM"
      ],
      "id": "31e6"
    },
    {
      "day": 4,
      "times": [
        "8:00 AM",
        "12:30 PM",
        "4:30 PM",
        "7:30 PM"
      ],
      "id": "c58e"
    },
    {
      "day": 5,
      "times": [
        "7:30 AM",
        "11:30 AM",
        "3:30 PM",
        "7:30 PM"
      ],
      "id": "f580"
    },
    {
      "day": 6,
      "times": [
        "7:00 AM",
        "11:00 AM",
        "2:00 PM",
        "6:00 PM"
      ],
      "id": "b6e9"
    },
    {
      "day": 7,
      "times": [
        "8:30 AM",
        "12:00 PM",
        "4:00 PM",
        "8:00 PM"
      ],
      "id": "ab85"
    },
    {
      "day": "08",
      "times": [
        "7:00 AM",
        "11:30 AM",
        "3:00 PM",
        "8:30 PM"
      ],
      "id": "c6e7"
    },
    {
      "day": 9,
      "times": [
        "8:00 AM",
        "12:00 PM",
        "4:00 PM",
        "7:00 PM"
      ],
      "id": "b02e"
    },
    {
      "day": "10",
      "times": [
        "8:30 PM",
        "11:00 AM",
        "2:30 PM",
        "6:00 PM"
      ],
      "id": "cc67"
    },
    {
      "day": "11",
      "slots": [
        "8:00 AM",
        "12:30 PM",
        "4:30 PM",
        "8:00 PM"
      ],
      "id": "c9b7"
    },
    {
      "day": "12",
      "slots": [
        "8:00 AM",
        "11:30 AM",
        "3:00 PM",
        "7:00 PM"
      ],
      "id": "a9c6"
    },
    {
      "day": 13,
      "times": [
        "8:00 AM",
        "12:30 PM",
        "4:30 PM",
        "8:30 PM"
      ],
      "id": "2b16"
    },
    {
      "day": 14,
      "times": [
        "7:30 AM",
        "11:00 AM",
        "3:00 PM",
        "7:00 PM"
      ],
      "id": "f07a"
    },
    {
      "day": 15,
      "times": [
        "7:30 AM",
        "12:00 PM",
        "4:00 PM",
        "8:00 PM"
      ],
      "id": "1a94"
    },
    {
      "day": 16,
      "times": [
        "8:00 AM",
        "12:30 PM",
        "4:00 PM",
        "7:30 PM"
      ],
      "id": "3121"
    },
    {
      "day": "17",
      "times": [
        "7:00 AM",
        "3:30 PM",
        "7:30 PM"
      ],
      "id": "183f"
    },
    {
      "day": 18,
      "times": [
        "8:30 AM",
        "12:00 PM",
        "4:30 PM",
        "8:00 PM"
      ],
      "id": "f8bc"
    },
    {
      "day": "19",
      "times": [
        "7:30 AM",
        "11:00 AM",
        "4:00 PM",
        "6:30 PM"
      ],
      "id": "4868"
    },
    {
      "day": "20",
      "times": [
        "7:00 AM",
        "2:30 PM",
        "7:00 PM"
      ],
      "id": "1df5"
    },
    {
      "day": 21,
      "times": [
        "8:00 AM",
        "12:00 PM",
        "4:00 PM",
        "8:30 PM"
      ],
      "id": "a542"
    },
    {
      "day": 22,
      "times": [
        "7:30 AM",
        "11:00 AM",
        "3:30 PM",
        "7:30 PM"
      ],
      "id": "9b5a"
    },
    {
      "day": 23,
      "times": [
        "8:00 AM",
        "12:30 PM",
        "4:00 PM",
        "8:00 PM"
      ],
      "id": "3c9e"
    },
    {
      "day": 24,
      "times": [
        "7:30 AM",
        "11:30 AM",
        "3:00 PM",
        "7:30 PM"
      ],
      "id": "3eaf"
    },
    {
      "day": "25",
      "times": [],
      "id": "57df"
    },
    {
      "day": 26,
      "times": [
        "8:00 AM",
        "12:30 PM",
        "4:30 PM",
        "8:00 PM"
      ],
      "id": "8ae0"
    },
    {
      "day": 27,
      "times": [
        "7:00 AM",
        "11:30 AM",
        "3:00 PM",
        "7:30 PM"
      ],
      "id": "aff9"
    },
    {
      "day": 28,
      "times": [
        "8:30 AM",
        "12:00 PM",
        "4:30 PM",
        "8:00 PM"
      ],
      "id": "9a7b"
    },
    {
      "day": 29,
      "times": [
        "7:30 AM",
        "11:30 AM",
        "3:00 PM",
        "7:00 PM"
      ],
      "id": "3aa4"
    },
    {
      "day": 30,
      "times": [
        "8:00 AM",
        "12:00 PM",
        "4:00 PM",
        "8:30 PM"
      ],
      "id": "3e24"
    },
    {
      "day": 30,
      "times": [
        "9:00 AM",
        "12:30 PM",
        "4:30 PM",
        "8:00 PM"
      ],
      "id": "c705"
    }
  ]
}